LICENSE
MANIFEST.in
README.md
setup.py
eng_libpythonpro.egg-info/PKG-INFO
eng_libpythonpro.egg-info/SOURCES.txt
eng_libpythonpro.egg-info/dependency_links.txt
eng_libpythonpro.egg-info/not-zip-safe
eng_libpythonpro.egg-info/requires.txt
eng_libpythonpro.egg-info/top_level.txt
libpythonpro/__init__.py
libpythonpro/github_api.py