Metadata-Version: 2.1
Name: eng-libpythonpro
Version: 0.2
Summary: Módulo para exemplificar construção de projetos Python no curso PyTools
Home-page: https://github.com/engnogueira/libpythonpro
Author: Gilson Nogueira
Author-email: engnogueira@hotmail.com
License: GNU Affero General Public License v3 or later (AGPLv3+)
Platform: UNKNOWN
Classifier: Development Status :: 2 - Pre-Alpha
Classifier: Environment :: Console
Classifier: Intended Audience :: Developers
Classifier: License :: OSI Approved :: GNU Affero General Public License v3 or later (AGPLv3+)
Classifier: Operating System :: OS Independent
Classifier: Programming Language :: Python
Classifier: Programming Language :: Python :: 3.7
Classifier: Framework :: Pytest
